yang.ncdiff-25.9-py3.13-nspkg.pth
yang/ncdiff/__init__.py
yang/ncdiff/calculator.py
yang/ncdiff/composer.py
yang/ncdiff/config.py
yang/ncdiff/device.py
yang/ncdiff/errors.py
yang/ncdiff/gnmi.py
yang/ncdiff/model.py
yang/ncdiff/netconf.py
yang/ncdiff/ref.py
yang/ncdiff/restconf.py
yang/ncdiff/runningconfig.py
yang/ncdiff/plugins/__init__.py
yang/ncdiff/plugins/cxml.py
yang/ncdiff/plugins/pyimport.py
yang/ncdiff/tests/__init__.py
yang/ncdiff/tests/test_ncdiff.py
yang/ncdiff/tests/test_running_config.py
yang/ncdiff/tests/yang/$dependencies.xml
yang/ncdiff/tests/yang/ATM-FORUM-TC-MIB.yang
yang/ncdiff/tests/yang/ATM-MIB.yang
yang/ncdiff/tests/yang/ATM-TC-MIB.yang
yang/ncdiff/tests/yang/BGP4-MIB.yang
yang/ncdiff/tests/yang/BRIDGE-MIB.yang
yang/ncdiff/tests/yang/CISCO-AAA-SERVER-MIB.yang
yang/ncdiff/tests/yang/CISCO-AAA-SESSION-MIB.yang
yang/ncdiff/tests/yang/CISCO-AAL5-MIB.yang
yang/ncdiff/tests/yang/CISCO-ATM-EXT-MIB.yang
yang/ncdiff/tests/yang/CISCO-ATM-PVCTRAP-EXTN-MIB.yang
yang/ncdiff/tests/yang/CISCO-ATM-QOS-MIB.yang
yang/ncdiff/tests/yang/CISCO-BGP-POLICY-ACCOUNTING-MIB.yang
yang/ncdiff/tests/yang/CISCO-BGP4-MIB.yang
yang/ncdiff/tests/yang/CISCO-BULK-FILE-MIB.yang
yang/ncdiff/tests/yang/CISCO-CBP-TARGET-MIB.yang
yang/ncdiff/tests/yang/CISCO-CBP-TARGET-TC-MIB.yang
yang/ncdiff/tests/yang/CISCO-CBP-TC-MIB.yang
yang/ncdiff/tests/yang/CISCO-CDP-MIB.yang
yang/ncdiff/tests/yang/CISCO-CEF-MIB.yang
yang/ncdiff/tests/yang/CISCO-CEF-TC.yang
yang/ncdiff/tests/yang/CISCO-CONFIG-COPY-MIB.yang
yang/ncdiff/tests/yang/CISCO-CONFIG-MAN-MIB.yang
yang/ncdiff/tests/yang/CISCO-CONTEXT-MAPPING-MIB.yang
yang/ncdiff/tests/yang/CISCO-DATA-COLLECTION-MIB.yang
yang/ncdiff/tests/yang/CISCO-DIAL-CONTROL-MIB.yang
yang/ncdiff/tests/yang/CISCO-DOT3-OAM-MIB.yang
yang/ncdiff/tests/yang/CISCO-DYNAMIC-TEMPLATE-MIB.yang
yang/ncdiff/tests/yang/CISCO-DYNAMIC-TEMPLATE-TC-MIB.yang
yang/ncdiff/tests/yang/CISCO-EIGRP-MIB.yang
yang/ncdiff/tests/yang/CISCO-EMBEDDED-EVENT-MGR-MIB.yang
yang.ncdiff-25.9.dist-info/METADATA
yang.ncdiff-25.9.dist-info/WHEEL
yang.ncdiff-25.9.dist-info/namespace_packages.txt
yang.ncdiff-25.9.dist-info/top_level.txt
yang.ncdiff-25.9.dist-info/RECORD
